pywnedpasswords/__init__.py
pywnedpasswords/pywnedpasswords.py
pywnedpasswords/tests/__init__.py
pywnedpasswords/tests/test_pywnedpasswords.py
pywnedpasswords-0.61.dist-info/DESCRIPTION.rst
pywnedpasswords-0.61.dist-info/METADATA
pywnedpasswords-0.61.dist-info/RECORD
pywnedpasswords-0.61.dist-info/WHEEL
pywnedpasswords-0.61.dist-info/entry_points.txt
pywnedpasswords-0.61.dist-info/metadata.json
pywnedpasswords-0.61.dist-info/top_level.txt
