Metadata-Version: 2.0
Name: pywnedpasswords
Version: 0.61
Summary: Client for HIBP passwords api using K-Anonymity method
Home-page: http://github.com/xmatthias/pywnedpasswords
Author: Matthias Voppichler
Author-email: xmatthias@outlook.com
License: MIT
Project-URL: Source Code, http://github.com/xmatthias/pywnedpasswords
Keywords: pwnedpasswords,passwords,pwned,security
Platform: UNKNOWN
Requires-Python: >=3
Requires-Dist: requests (>=2)
